{"classification": ["bill"], "extras": {}, "_id": "5e953564-7b68-11e5-a9c0-1040f380f686", "title": "Ord. relating to present and future funding for certain services provided to the Bi-State Dev. Agency", "related_bills": [], "legislative_session": "2010-2011", "other_identifiers": [], "other_titles": [], "actions": [{"classification": ["reading-1"], "organization_id": "~{\"classification\": \"legislature\"}", "date": "2010-06-11", "description": "reading-1", "related_entities": []}, {"classification": ["reading-2"], "organization_id": "~{\"classification\": \"legislature\"}", "date": "2010-07-02", "description": "reading-2", "related_entities": []}, {"classification": ["committee-referral"], "organization_id": "~{\"classification\": \"legislature\"}", "date": "2010-07-09", "description": "committee-referral", "related_entities": []}, {"classification": ["filing"], "organization_id": "~{\"classification\": \"legislature\"}", "date": "2010-09-17", "description": "filing", "related_entities": []}], "subject": [], "abstracts": [{"date": "", "note": "summary", "abstract": "BOARD BILL NO. 97\tINTRODUCED BY:  ALDERWOMEN JENNIFER \t\t\t\tFLORIDA AND MARLENE DAVIS AND ALDERMEN \t\t\tCHARLES Q. TROUPE AND CRAIG SCHMID  AN ORDINANCE RELATING TO PRESENT AND FUTURE FUNDING FOR CERTAIN SERVICES PROVIDED TO THE BI-STATE DEVELOPMENT AGENCY BY THE CITY IN THE GATEWAY TRANSPORTATION CENTER AND BY THE PURCHASE OF CERTAIN TRASH RECEPTACLES, MAINTENANCE THEREOF AND TRASH REMOVAL BY THE CITY AND PROVIDING FOR THE USE OF THE PROCEEDS FROM A TRANSPORTATION TRUST FUND FOR SAID SERVICES AND PURCHASE BY THE CITY.  "}], "identifier": "BB 97", "from_organization": "~{\"classification\": \"legislature\"}", "documents": [], "sources": [{"url": "https://www.stlouis-mo.gov/government/departments/aldermen/city-laws/board-bills.cfm?bbDetail=true&BBId=6268", "note": "detail"}], "sponsorships": [{"classification": "Primary", "name": "Jennifer Florida ", "person_id": "~{\"name\": \"Jennifer Florida \"}", "entity_type": "person", "organization_id": null, "primary": true}, {"classification": "co-sponsor", "name": "Charles Troupe", "person_id": "~{\"name\": \"Charles Troupe\"}", "entity_type": "person", "organization_id": null, "primary": false}, {"classification": "co-sponsor", "name": "Marlene Davis", "person_id": "~{\"name\": \"Marlene Davis\"}", "entity_type": "person", "organization_id": null, "primary": false}, {"classification": "co-sponsor", "name": "Craig Schmid", "person_id": "~{\"name\": \"Craig Schmid\"}", "entity_type": "person", "organization_id": null, "primary": false}], "versions": []}