{"classification": ["bill"], "extras": {}, "_id": "dd019c9c-7b67-11e5-8b4b-1040f380f686", "title": "Zoning change for properties on Thomas", "related_bills": [], "legislative_session": "2010-2011", "other_identifiers": [], "other_titles": [], "actions": [{"classification": ["reading-1"], "organization_id": "~{\"classification\": \"legislature\"}", "date": "2010-04-30", "description": "reading-1", "related_entities": []}, {"classification": ["reading-2"], "organization_id": "~{\"classification\": \"legislature\"}", "date": "2010-05-28", "description": "reading-2", "related_entities": []}, {"classification": ["committee-referral"], "organization_id": "~{\"classification\": \"legislature\"}", "date": "2010-06-04", "description": "committee-referral", "related_entities": []}, {"classification": ["reading-3"], "organization_id": "~{\"classification\": \"legislature\"}", "date": "2010-06-11", "description": "reading-3", "related_entities": []}], "subject": [], "abstracts": [{"date": "", "note": "summary", "abstract": "BOARD BILL NO.  3 INTRODUCED BY ALDERMAN MARLENE DAVIS    \tAn Ordinance recommended by the Planning Commission on April 7, 2010, to change the zoning of property as indicated on the District Map, from \"F\" Neighborhood Commercial District to the \"C\" Multiple-Family Dwelling District, in City Blocks 1004 and 1005 (2955, 2957, 2954 and 2956 Thomas), so as to include the described parcels of land in City Blocks 1004 and 1005; and containing an emergency clause.  "}], "identifier": "BB 3", "from_organization": "~{\"classification\": \"legislature\"}", "documents": [], "sources": [{"url": "https://www.stlouis-mo.gov/government/departments/aldermen/city-laws/board-bills.cfm?bbDetail=true&BBId=6073", "note": "detail"}], "sponsorships": [{"classification": "Primary", "name": "Marlene Davis\n", "person_id": "~{\"name\": \"Marlene Davis\\n\"}", "entity_type": "person", "organization_id": null, "primary": true}], "versions": []}