{"classification": ["bill"], "extras": {}, "_id": "11e18854-7b69-11e5-bf3e-1040f380f686", "title": "Casino bill", "related_bills": [], "legislative_session": "2010-2011", "other_identifiers": [], "other_titles": [], "actions": [], "subject": [], "abstracts": [{"date": "", "note": "summary", "abstract": "BOARD BILL NO. 228\t    INTRODUCED BY ALDERWOMAN DIONNE FLOWERS    AN ORDINANCE TO ESTABLISH A BOARD TO REVIEW AND RECOMMEND PUBLIC WORK PROJECTS TO BE APPROVED BY THE BOARD OF PUBLIC SERVICE PURSUANT TO SECTION 3.16 OF THAT CERTAIN DEVELOPMENT AGREEMENT DATED OCTOBER 19, 2010 BETWEEN THE PORT AUTHORITY OF THE CITY OF ST. LOUIS AND CASINO CELEBRATION, LLC WHICH DEVELOPMENT AGREEMENT APPROVED A NEW CITY GAMING DEVELOPMENT PLAN; AUTHORIZING CERTAIN ACTIONS BY CITY OFFICIALS; AND CONTAINING A SEVERABILITY CLAUSE.    "}], "identifier": "BB 228", "from_organization": "~{\"classification\": \"legislature\"}", "documents": [], "sources": [{"url": "https://www.stlouis-mo.gov/government/departments/aldermen/city-laws/board-bills.cfm?bbDetail=true&BBId=6702", "note": "detail"}], "sponsorships": [{"classification": "Primary", "name": "Dionne Flowers ", "person_id": "~{\"name\": \"Dionne Flowers \"}", "entity_type": "person", "organization_id": null, "primary": true}], "versions": []}